<?xml version="1.0" encoding="UTF-8" ?>
<templates xml:space="preserve">
    <t t-name="awesome_owl.TodoItem">
        <div t-att-class="props.todo.isCompleted ? 'text-decoration-line-through text-muted' : '' ">
            <input class="form-check-input" type="checkbox"
                   t-att-checked="props.todo.isCompleted"
                   t-on-change="onChange"/>
            <t t-esc="props.todo.id"/>.
            <t t-esc="props.todo.description"/>
            <span role="Button" class="fa fa-remove" t-on-click="onRemove"/>
        </div>
    </t>
</templates>