<?xml version="1.0" encoding="utf-8"?>
<odoo>

    <record id="real_estate.view_properties_action" model="ir.actions.act_window">
        <field name="name">Properties</field>
        <field name="res_model">real.estate.property</field>
        <field name="context">{'search_default_filter_for_sale': True}</field>
        <field name="view_mode">list,form</field>
        <field name="help" type="html">
            <!-- Turns out I didn't feel like being creative with the help text ¯\_(ツ)_/¯ -->
            <p class="o_view_nocontent_smiling_face">
                Create a new property.
            </p>
        </field>
    </record>

    <record id="real_estate.property_list" model="ir.ui.view">
        <field name="name">Property List</field>
        <field name="model">real.estate.property</field>
        <field name="arch" type="xml">
            <list>
                <field name="name"/>
                <field name="state"/>
                <field name="type_id"/>
                <field name="selling_price"/>
                <field name="availability_date"/>
                <field name="floor_area" optional="show"/>
                <field name="bedrooms" optional="hide"/>
                <field name="has_garage" optional="hide"/>
                <field name="has_garden" optional="hide"/>
                <field name="garden_area" optional="hide"/>
            </list>
        </field>
    </record>

    <record id="real_estate.property_form" model="ir.ui.view">
        <field name="name">Property Form</field>
        <field name="model">real.estate.property</field>
        <field name="arch" type="xml">
            <form>
                <header>
                    <field name="state" widget="statusbar" options="{'clickable': True}"/>
                </header>
                <sheet>
                    <field name="image" widget="image" class="oe_avatar"/>
                    <div class="oe_title">
                        <label for="name" string="Property Name"/>
                        <h1>
                            <field name="name" placeholder="e.g. Tiny House"/>
                        </h1>
                    </div>
                    <group>
                        <group string="Listing Information">
                            <field name="type_id"/>
                            <field name="selling_price"/>
                            <field name="availability_date"/>
                            <field name="active"/>
                        </group>
                        <group string="Building Specifications">
                            <field name="floor_area"/>
                            <field name="bedrooms"/>
                            <field name="has_garage"/>
                            <field name="has_garden"/>
                            <field name="garden_area"/>
                        </group>
                    </group>
                    <notebook>
                        <page string="Description">
                            <field
                                name="description"
                                placeholder="Write a description about this property."
                            />
                        </page>
                        <page string="Other Info">
                            <group>
                                <group>
                                    <field name="address_id"/>
                                    <field name="seller_id"/>
                                    <field name="salesperson_id"/>
                                </group>
                            </group>
                        </page>
                    </notebook>
                </sheet>
            </form>
        </field>
    </record>

    <record id="real_estate.property_search" model="ir.ui.view">
        <field name="name">Property Search</field>
        <field name="model">real.estate.property</field>
        <field name="arch" type="xml">
            <search>
                <!-- Fields -->
                <field name="name"/>
                <field
                    name="description"
                    filter_domain="['|', ('name', 'ilike', self), ('description', 'ilike', self)]"
                />
                <field name="selling_price" string="Maximum Price" operator="&lt;="/>
                <field name="floor_area" string="Minimum Floor Area" operator="&gt;="/>
                <field name="bedrooms" string="Minimum Bedrooms" operator="&gt;="/>

                <!-- Filters -->
                <filter
                    name="filter_for_sale"
                    string="For Sale"
                    domain="[('state', 'in', ['new', 'offer_received'])]"
                />
                <separator/>
                <filter name="filter_availability" date="availability_date"/>
                <separator/>
                <filter name="filter_garage" string="Garage" domain="[('has_garage', '=', True)]"/>
                <filter name="filter_garden" string="Garden" domain="[('has_garden', '=', True)]"/>
                <separator/>
                <filter name="filter_inactive" string="Archived" domain="[('active', '=', False)]"/>

                <!-- Group by -->
                <filter name="group_by_state" context="{'group_by': 'state'}"/>
                <filter name="group_by_type" context="{'group_by': 'type_id'}"/>
            </search>
        </field>
    </record>

</odoo>
