<?xml version="1.0"?>
<odoo>
    <!-- Form view-->
    <record id="estate_property_offer_view_form" model="ir.ui.view">
        <field name="name">estate.property.offer.form</field>
        <field name="model">estate.property.offer</field>
        <field name="arch" type="xml">
            <form string="Property Offer Form View">
                <sheet>
                    <group>
                        <group>
                            <field name="price"/>
                            <field name="status"/>
                        </group>
                        <group>
                            <field name="property_id"/>
                            <field name="partner_id"/>
                        </group>
                    </group>
                </sheet>
            </form>
        </field>
    </record>

    <!-- Tree view -->
    <record id="estate_property_offer_view_tree" model="ir.ui.view">
        <field name="name">estate.property.offer.tree</field>
        <field name="model">estate.property.offer</field>
        <field name="arch" type="xml">
            <tree string="Property Offer Tree">
                <field name="price"/>
                <field name="partner_id"/>
                <field name="status"/>
            </tree>
        </field>
    </record>
</odoo>