<?xml version="1.0" encoding="UTF-8"?>
<odoo>
    <record id="estate_property_search_view" model="ir.ui.view">
        <field name="name">estate.property.search</field>
        <field name="model">estate.property</field>
        <field name="arch" type="xml">
            <search string="Search...">
                <field name="name" string="Title"/>
                <field name="postcode"/>
                <field name="expected_price"/>
                <field name="bedrooms"/>
                <field name="living_area"/>
                <field name="facades"/>
                <!-- filter -->
                <filter string="Available" name="available" domain="['|', ('state', '=', 'new'), ('state', '=', 'offer_received')]"/>
                <!-- group by -->
                <filter string="Postcode" name="group_by_postcode" context="{'group_by':'postcode'}"/>
            </search>
        </field>
    </record>
</odoo>

