<?xml version="1.0" encoding="utf-8"?>
<odoo>

    <record id="action_estate_property_type" model="ir.actions.act_window">
        <field name="name">Property Types</field>
        <field name="res_model">estate.property.type</field>
        <field name="view_mode">tree,form</field>
        <field name="help" type="html">
            <p class="o_view_nocontent_smiling_face"> Create a property type</p>
        </field>

    </record>


    <record id="view_estate_property_type_tree" model="ir.ui.view">
        <field name="name">estate.property.type.tree</field>
        <field name="model">estate.property.type</field>
        <field name="arch" type="xml">
            <tree>
                <field name="sequence" widget="handle" />
                <field name="name"/>
            </tree>
        </field>
    </record>

    <record id="view_estate_property_type_form" model="ir.ui.view">
        <field name="name">estate.property.type.form</field>
        <field name="model">estate.property.type</field>
        <field name="arch" type="xml">
            <form string="Property Type">
            <header>
                <button type="action" name="%(estate.action_estate_property_offer)d" string="Offers" class="oe_stat_button" icon="fa-archive" style= "align: right;">
                </button>
            </header>
                <sheet>
                     <div>
                        <h1><field name="name"/></h1>
                        <field name="offer_count" readonly="1"/>
                    </div>
                    <notebook>
                        <page string="Properties">
                            <field name="property_ids">
                                <tree editable="bottom">
                                    <field name="title"/>
                                    <field name="expected_price"/>
                                    <field name="selling_price"/>
                                    <field name="state"/>
                                </tree>
                            </field>
                        </page>
                    </notebook>
                </sheet>
               
            </form>
        </field>
    </record>


    

</odoo>
